chika/__init__.py
chika/chika.py
chika/utils.py
chika-0.1.0.dist-info/LICENSE
chika-0.1.0.dist-info/METADATA
chika-0.1.0.dist-info/WHEEL
chika-0.1.0.dist-info/top_level.txt
chika-0.1.0.dist-info/RECORD
