Metadata-Version: 2.1
Name: chika
Version: 0.1.0
Summary: chika: a dataclass-based simple and easy config tool
Home-page: https://github.com/moskomule/chika
Author: Ryuichiro Hataya
License: UNKNOWN
Platform: UNKNOWN
Classifier: Development Status :: 3 - Alpha
Classifier: Intended Audience :: Developers
Classifier: License :: OSI Approved :: MIT License
Classifier: Programming Language :: Python :: 3.9
Requires-Python: >=3.9
License-File: LICENSE
Requires-Dist: pyyaml
